pystreet/__init__.py
pystreet/automaton.py
pystreet/data.py
pystreet/geocoder.py
pystreet/validator.py
pystreet-1.0.0.dist-info/LICENSE
pystreet-1.0.0.dist-info/METADATA
pystreet-1.0.0.dist-info/WHEEL
pystreet-1.0.0.dist-info/top_level.txt
pystreet-1.0.0.dist-info/RECORD
